src/reader/__init__.py
src/reader/__main__.py
src/reader/config.toml
src/reader/feed.py
src/reader/viewer.py
gvodolagin_reader-0.1.0.dist-info/LICENSE
gvodolagin_reader-0.1.0.dist-info/WHEEL
gvodolagin_reader-0.1.0.dist-info/METADATA
gvodolagin_reader-0.1.0.dist-info/RECORD
